finance/__init__.py
finance/urls.py
finance/apps/__init__.py
finance/apps/budget.py
finance/apps/dashboard.py
finance/apps/financing_agency_app.py
finance/apps/grant_app.py
finance/apps/grant_domain_app.py
finance/apps/costcenter/__init__.py
finance/apps/costcenter/costcenter_list.py
finance/apps/costcenter/expensecode_form.py
finance/apps/costcenter/expensecode_list.py
finance/apps/costcenter/financeproject_form.py
finance/apps/costcenter/financeproject_list.py
finance/fixtures/initial_data.yaml
finance/management/__init__.py
finance/management/commands/__init__.py
finance/management/commands/import_orders.py
finance/management/commands/validate_orders.py
finance/migrations/0001_initial.py
finance/migrations/__init__.py
finance/models/__init__.py
finance/models/budget/__init__.py
finance/models/budget/budget.py
finance/models/budget/budget_doc.py
finance/models/costcenter/__init__.py
finance/models/costcenter/costcenter.py
finance/models/costcenter/costcenter_queryset.py
finance/models/grant/__init__.py
finance/models/grant/financing_agency.py
finance/models/grant/grant.py
finance/models/grant/grant_domain.py
finance/models/project/__init__.py
finance/models/project/expense_code.py
finance/models/project/project.py
finance/models/project/project_queryset.py
core_finance-0.3.dist-info/METADATA
core_finance-0.3.dist-info/WHEEL
core_finance-0.3.dist-info/top_level.txt
core_finance-0.3.dist-info/RECORD
