Metadata-Version: 2.1
Name: core-finance
Version: 0.3
Summary: Research CORE ERM - finance module
Home-page: https://github.com/research-core/core-finance
Author: Ricardo Ribeiro, Hugo Cachitas
Author-email: ricardojvr@gmail.com, hugo.cachitas@research.fchampalimaud.org
License: MIT
Platform: UNKNOWN
Requires-Dist: xlrd
Requires-Dist: openpyxl
